{
  "capabilities": [
    "eye",
    "expression"
  ],
  "dependencies": [],
  "entry_assembly": "OpenVRPair.FaceTracking.VrcftCompat.dll",
  "entry_type": "OpenVRPair.FaceTracking.VrcftCompat.ReflectingExtTrackingModuleAdapter",
  "min_host_version": "1.0",
  "name": "MeowFaceTrackingModule",
  "platforms": [
    "windows-x64"
  ],
  "schema": 1,
  "sdk_version": "1.0",
  "supported_hmds": [
    "*"
  ],
  "uuid": "227be6c2-7ed7-536b-8913-825fcf075b26",
  "vendor": "azmidi",
  "version": "1.3"
}
